refit/__init__.py
refit/host.py
refit/main.py
refit/registry.py
refit/task.py
refit/mixins/__init__.py
refit/mixins/apt.py
refit/mixins/base.py
refit/mixins/docker.py
refit/mixins/file.py
refit/mixins/path.py
refit/mixins/python.py
refit/mixins/template.py
refit/scaffold/__init__.py
refit/scaffold/main.py
refit/scaffold/files/files.md
refit/scaffold/files/templates.md
refit/scaffold/templates/base.py.jinja
refit/scaffold/templates/hosts.py.jinja
refit/scaffold/templates/settings.py.jinja
refit/scaffold/templates/tasks.py.jinja
tests/mixins/__init__.py
tests/mixins/test_apt.py
tests/task/__init__.py
tests/task/test_connection.py
tests/task/test_decorator.py
tests/task/test_function_register.py
tests/task/test_sequence.py
tests/task/test_tags.py
refit-0.3.0.dist-info/METADATA
refit-0.3.0.dist-info/WHEEL
refit-0.3.0.dist-info/entry_points.txt
refit-0.3.0.dist-info/top_level.txt
refit-0.3.0.dist-info/RECORD
