Metadata-Version: 2.1
Name: refit
Version: 0.3.0
Summary: Simple remote server configuration, using asyncio.
Home-page: https://github.com/dantownsend/refit
Author: Daniel Townsend
Author-email: dan@dantownsend.co.uk
License: MIT
Platform: UNKNOWN
Classifier: License :: OSI Approved :: MIT License
Classifier: Programming Language :: Python
Classifier: Programming Language :: Python :: 3
Classifier: Programming Language :: Python :: 3.7
Classifier: Programming Language :: Python :: 3.8
Classifier: Programming Language :: Python :: Implementation :: CPython
Classifier: Development Status :: 2 - Pre-Alpha
Requires-Python: >=3.7.0
Requires-Dist: asyncssh (==2.2.1)
Requires-Dist: uvloop (==0.14.0)
Requires-Dist: jinja2 (==2.11.2)
Requires-Dist: aiohttp (==3.6.2)
Requires-Dist: termcolor (==1.1.0)
Requires-Dist: targ (==0.1.3)
